diacritics_normalization/__init__.py
diacritics_normalization-0.1.0.dist-info/METADATA
diacritics_normalization-0.1.0.dist-info/WHEEL
diacritics_normalization-0.1.0.dist-info/top_level.txt
diacritics_normalization-0.1.0.dist-info/RECORD
