Metadata-Version: 2.4
Name: diacritics-normalization
Version: 0.1.0
Summary: A small utility library that normalize hebrew diacritics in text.
Author-email: Eyal Cohen <eyalcohenx@gmail.com>
Classifier: Programming Language :: Python :: 3
Requires-Python: >=3.7
